#######################################################################################################################################
<poster>Kodi King TV</poster>
<fanart>http://www.argenteam.net/resources/images/e2f10b67d4f79fd30d8794fd7cdaae15.jpg</fanart>
#######################################################################################################################################

<item>
<title>Episode 1</title>
<link>http://vodlocker.com/5i8rl0jtwr6d</link>
<thumbnail>http://ifanboy.com/wp-content/uploads/2011/12/Storyteller-Cover.jpg</thumbnail>
</item>

<item>
<title>Episode 2</title>
<link>http://dai.ly/x1zl5h</link>
<thumbnail>http://ifanboy.com/wp-content/uploads/2011/12/Storyteller-Cover.jpg</thumbnail>
</item>

<item>
<title>Pitch Perfect - I've Got The Magic In Me (Boys Final)</title>
<link>https://www.youtube.com/watch?v=oSsQsFS8Us0</link>
<thumbnail>http://ifanboy.com/wp-content/uploads/2011/12/Storyteller-Cover.jpg</thumbnail>
</item>
